keta_python_sdk/__init__.py
keta_python_sdk/client.py
keta_python_sdk/entity.py
keta_python_sdk/errors.py
keta_python_sdk/on_demand_action.py
keta_python_sdk/api/__init__.py
keta_python_sdk/api/on_demand_api.py
keta_python_sdk/api/packet.py
keta_python_sdk/api/response.py
keta_python_sdk/common/__init__.py
keta_python_sdk/common/logging.py
keta_python_sdk/sched_task/__init__.py
keta_python_sdk/sched_task/on_demand_sched_task.py
keta_python_sdk/sched_task/sched_task_param.py
keta_python_sdk/schedule/__init__.py
keta_python_sdk/schedule/job.py
keta_python_sdk/schedule/task.py
keta_python_sdk/spl/__init__.py
keta_python_sdk/spl/spl_base_command.py
keta_python_sdk/spl/spl_generating_command.py
keta_python_sdk/spl/spl_packet_utils.py
keta_python_sdk/spl/spl_streaming_batch_command.py
keta_python_sdk/spl/spl_streaming_chunk_command.py
keta_python_sdk/spl/spl_streaming_command.py
keta_python_sdk/storage/__init__.py
keta_python_sdk/storage/base.py
keta_python_sdk/storage/client.py
keta_python_sdk/storage/record.py
keta_python_sdk/tools/__init__.py
keta_python_sdk/tools/mock_tools.py
keta_python_sdk/trigger_action/__init__.py
keta_python_sdk/trigger_action/on_demand_trigger_action.py
keta_python_sdk/trigger_action/trigger_action_param.py
keta_python_sdk-2.0.4.dist-info/METADATA
keta_python_sdk-2.0.4.dist-info/WHEEL
keta_python_sdk-2.0.4.dist-info/top_level.txt
keta_python_sdk-2.0.4.dist-info/RECORD
