Metadata-Version: 2.1
Name: keta-python-sdk
Version: 2.0.4
Summary: keta python sdk, simple to integrate with ketaops
Home-page: https://gitee.com/xishuhq/keta-python-sdk
Author: keta
Author-email: ketaops@xishuhq.com
License: Apache-2.0
Project-URL: Documentation, https://xishuhq.com
Project-URL: Source, https://gitee.com/xishuhq/keta-python-sdk
Project-URL: Tracker, https://gitee.com/xishuhq/keta-python-sdk/issues
Keywords: xishu,ketaops,sdk
Platform: any
